jupyteach_jupyterlite_contents/__init__.py
jupyteach_jupyterlite_contents/_version.py
jupyteach_jupyterlite_contents-0.1.7.data/data/share/jupyter/labextensions/@jupyteach/jupyterlite-contents/package.json
jupyteach_jupyterlite_contents-0.1.7.data/data/share/jupyter/labextensions/@jupyteach/jupyterlite-contents/static/245.58357312172a3f5cb55d.js
jupyteach_jupyterlite_contents-0.1.7.data/data/share/jupyter/labextensions/@jupyteach/jupyterlite-contents/static/747.2513d2e0c0b80694bc02.js
jupyteach_jupyterlite_contents-0.1.7.data/data/share/jupyter/labextensions/@jupyteach/jupyterlite-contents/static/935.274319fc9778b3d99890.js
jupyteach_jupyterlite_contents-0.1.7.data/data/share/jupyter/labextensions/@jupyteach/jupyterlite-contents/static/remoteEntry.af2e190a8b47717040b2.js
jupyteach_jupyterlite_contents-0.1.7.data/data/share/jupyter/labextensions/@jupyteach/jupyterlite-contents/static/style.js
jupyteach_jupyterlite_contents-0.1.7.data/data/share/jupyter/labextensions/@jupyteach/jupyterlite-contents/static/third-party-licenses.json
jupyteach_jupyterlite_contents-0.1.7.data/data/share/jupyter/labextensions/@jupyteach/jupyterlite-contents/install.json
jupyteach_jupyterlite_contents-0.1.7.dist-info/METADATA
jupyteach_jupyterlite_contents-0.1.7.dist-info/WHEEL
jupyteach_jupyterlite_contents-0.1.7.dist-info/licenses/LICENSE
jupyteach_jupyterlite_contents-0.1.7.dist-info/RECORD
